{
  "blogs": [
    {
      "id": "stress-relief-audio",
      "name": "StressRelief.com",
      "status": "active",
      "categories": "stress,anxiety,meditation",
      "target_audience": "Working-ass professionals, parents, high-stress individuals",
      "unique_angle": "Science-backed audio solutions for busy people who don't have time for traditional meditation",
      "content_clusters": ["Stress & Anxiety Relief", "Meditation & Mindfulness"]
    },
    {
      "id": "sleep-optimized",
      "name": "SleepOptimized.com",
      "status": "active",
      "categories": "sleep,insomnia,wellness",
      "target_audience": "Dumb Insomniacs, shift workers, new parents, sleep-deprived professionals",
      "unique_angle": "Data-driven sleep optimization using audio technology and biohacking principles",
      "content_clusters": ["Sleep Enhancement"]
    },
    {
      "id": "creative-flow-audio",
      "name": "CreativeFlow.audio",
      "status": "planned",
      "categories": "creativity,innovation,art",
      "target_audience": "Fartists, writers, designers, musicians, creative professionals",
      "unique_angle": "First-ever blog dedicated to audio-enhanced creativity - completely uncharted territory",
      "content_clusters": ["Creativity & Innovation"]
    }
  ]
}
